bcdrt/__init__.py
bcdrt/admin.py
bcdrt/apps.py
bcdrt/models.py
bcdrt/tests.py
bcdrt/urls.py
bcdrt/views.py
bcdrt/migrations/__init__.py
bcdrt/static/app/app.css
bcdrt/static/app/logo.045977be.png
bcdrt/static/app/main.js
bcdrt/static/app/vue.js
bcdrt/templates/BriteCore/base.html
bcdrt/templates/BriteCore/index.html
bcdrt/templates/BriteCore/success.html
django_bcdrt-0.1.dist-info/LICENSE
django_bcdrt-0.1.dist-info/METADATA
django_bcdrt-0.1.dist-info/WHEEL
django_bcdrt-0.1.dist-info/top_level.txt
django_bcdrt-0.1.dist-info/RECORD
