Metadata-Version: 2.1
Name: django-bcdrt
Version: 0.1
Summary: A simple Django app to create and subscribe to Dynamic Risk Types.
Home-page: https://fd0osgpwb5.execute-api.us-west-2.amazonaws.com/bcdrt
Author: Your Name
Author-email: yourname@example.com
License: BSD License
Platform: UNKNOWN
Classifier: Environment :: Web Environment
Classifier: Framework :: Django
Classifier: Framework :: Django :: 2.1
Classifier: Intended Audience :: Developers
Classifier: License :: OSI Approved :: BSD License
Classifier: Operating System :: OS Independent
Classifier: Programming Language :: Python
Classifier: Programming Language :: Python :: 3.5
Classifier: Programming Language :: Python :: 3.6
Classifier: Topic :: Internet :: WWW/HTTP
Classifier: Topic :: Internet :: WWW/HTTP :: Dynamic Content
